{
  "project_info": {
    "project_number": "661177673437",
    "project_id": "btutask2",
    "storage_bucket": "btutask2.appspot.com"
  },
  "client": [
    {
      "client_info": {
        "mobilesdk_app_id": "1:661177673437:android:2fc819f38080e2e9f11d34",
        "android_client_info": {
          "package_name": "com.example.firebaseAppBTU2"
        }
      },
      "oauth_client": [
        {
          "client_id": "661177673437-189pkj8s56n8nlhbjfaaofg16me3rl1s.apps.googleusercontent.com",
          "client_type": 3
        }
      ],
      "api_key": [
        {
          "current_key": "AIzaSyB6TVJvz9_mUfrvpE1JzhbkzUrH8czPVq8"
        }
      ],
      "services": {
        "appinvite_service": {
          "other_platform_oauth_client": [
            {
              "client_id": "661177673437-189pkj8s56n8nlhbjfaaofg16me3rl1s.apps.googleusercontent.com",
              "client_type": 3
            }
          ]
        }
      }
    }
  ],
  "configuration_version": "1"
}